gershgorin/__init__.py
gershgorin/gershgorin.py
gershgorin/version.py
gershgorin-0.0.0.dist-info/LICENSE
gershgorin-0.0.0.dist-info/METADATA
gershgorin-0.0.0.dist-info/WHEEL
gershgorin-0.0.0.dist-info/top_level.txt
gershgorin-0.0.0.dist-info/RECORD
