Metadata-Version: 2.1
Name: gershgorin
Version: 0.0.0
Summary: Visualize the Gershgorin discs that bound the spectrum of a square matrix.
Home-page: https://github.com/v715/gershgorin
Author: Vivek Gopalakrishnan
Author-email: vivekg@mit.edu
License: MIT
Platform: UNKNOWN
Classifier: Programming Language :: Python
Classifier: Programming Language :: Python :: 3
Classifier: Programming Language :: Python :: 3.6
Classifier: Programming Language :: Python :: 3.7
Classifier: Programming Language :: Python :: 3.8
Classifier: License :: OSI Approved :: MIT License
License-File: LICENSE
Requires-Dist: matplotlib
Requires-Dist: numpy
Requires-Dist: adjustText
